{"ProductID":"管壳式热交换器_BES","PartID":"043","OutPutName":"b管程出口开孔补强","Params":[{"Id":"A016001","Name":"压力等级","Value":"150","Desc":null,"ReportOutput":null},{"Id":"A016003","Name":"管箱接管法兰材料牌号","Value":"16Mn","Desc":null,"ReportOutput":null},{"Id":"A016004","Name":"管箱接管法兰材料类型","Value":"锻件","Desc":null,"ReportOutput":null},{"Id":"A016012","Name":"轴向定位值","Value":"默认","Desc":null,"ReportOutput":null},{"Id":"A016013","Name":"压力等级类型","Value":"class","Desc":null,"ReportOutput":null},{"Id":"A020046","Name":"公称直径单位","Value":"DN","Desc":null,"ReportOutput":null},{"Id":"A016002","Name":"公称直径","Value":"300","Desc":null,"ReportOutput":null},{"Id":"A016029","Name":"法兰主体型式","Value":"WN","Desc":null,"ReportOutput":null},{"Id":"A016030","Name":"密封面型式","Value":"RF","Desc":null,"ReportOutput":null}]}